castutils/__init__.py
castutils/builtins/__init__.py
castutils/builtins/booleans.py
castutils/builtins/floats.py
castutils/builtins/integers.py
castutils/builtins/strings.py
castutils/py.typed
castutils/types.py
castutils-0.2.5.dist-info/LICENSE
castutils-0.2.5.dist-info/WHEEL
castutils-0.2.5.dist-info/METADATA
castutils-0.2.5.dist-info/RECORD
